LICENSE.txt
MANIFEST.in
README.md
setup.py
docs/Makefile
docs/conf.py
docs/index.rst
docs/make.bat
docs/pySpacell.rst
docs/_build/doctrees/environment.pickle
docs/_build/doctrees/index.doctree
docs/_build/doctrees/pySpacell.doctree
docs/_build/html/.buildinfo
docs/_build/html/genindex.html
docs/_build/html/index.html
docs/_build/html/objects.inv
docs/_build/html/py-modindex.html
docs/_build/html/pySpacell.html
docs/_build/html/search.html
docs/_build/html/searchindex.js
docs/_build/html/_sources/index.rst.txt
docs/_build/html/_sources/pySpacell.rst.txt
docs/_build/html/_static/ajax-loader.gif
docs/_build/html/_static/alabaster.css
docs/_build/html/_static/basic.css
docs/_build/html/_static/comment-bright.png
docs/_build/html/_static/comment-close.png
docs/_build/html/_static/comment.png
docs/_build/html/_static/custom.css
docs/_build/html/_static/doctools.js
docs/_build/html/_static/documentation_options.js
docs/_build/html/_static/down-pressed.png
docs/_build/html/_static/down.png
docs/_build/html/_static/file.png
docs/_build/html/_static/jquery-3.2.1.js
docs/_build/html/_static/jquery.js
docs/_build/html/_static/language_data.js
docs/_build/html/_static/minus.png
docs/_build/html/_static/plus.png
docs/_build/html/_static/pygments.css
docs/_build/html/_static/searchtools.js
docs/_build/html/_static/underscore-1.3.1.js
docs/_build/html/_static/underscore.js
docs/_build/html/_static/up-pressed.png
docs/_build/html/_static/up.png
docs/_build/html/_static/websupport.js
pySpacell/__init__.py
pySpacell/_assortativity.py
pySpacell/_neighborhood_matrix.py
pySpacell/_randomizations.py
pySpacell/_ripley.py
pySpacell/_spatial_autocorrelation.py
pySpacell/_visualization.py
pySpacell/pySpacell.py
pySpacell.egg-info/PKG-INFO
pySpacell.egg-info/SOURCES.txt
pySpacell.egg-info/dependency_links.txt
pySpacell.egg-info/requires.txt
pySpacell.egg-info/top_level.txt
pySpacell/data/co-culture.csv
pySpacell/data/co-culture_label.tif
pySpacell/data/hepatocytes.csv
pySpacell/data/hepatocytes_3channels_crop.tiff
pySpacell/data/hepatocytes_crop.csv
pySpacell/data/hepatocytes_label.tif
pySpacell/data/hepatocytes_labels_crop.tiff
