Metadata-Version: 2.1
Name: pySpacell
Version: 0.1.1
Summary: A Python package for single cell spatial image analysis
Home-page: https://github.com/biocompibens/pySpacell
Author: France ROSE
Author-email: auguste.genovesio@ens.fr
License: MIT
Keywords: spatial analysis microscopy cells statistics
Platform: UNKNOWN
Classifier: Development Status :: 3 - Alpha
Classifier: License :: OSI Approved :: MIT License
Classifier: Programming Language :: Python :: 3.5
Classifier: Operating System :: OS Independent
